pptgen/__init__.py
pptgen/color.py
pptgen/colors.json
pptgen/commands.py
pptgen/fonts.json
pptgen/fontwidth.py
pptgen/release.json
pptgen/utils.py
pptgen-0.2.1.dist-info/DESCRIPTION.rst
pptgen-0.2.1.dist-info/METADATA
pptgen-0.2.1.dist-info/RECORD
pptgen-0.2.1.dist-info/WHEEL
pptgen-0.2.1.dist-info/entry_points.txt
pptgen-0.2.1.dist-info/metadata.json
pptgen-0.2.1.dist-info/top_level.txt
