Metadata-Version: 2.0
Name: pptgen
Version: 0.2.1
Summary: Make PowerPoint presentations from data
Home-page: http://code.gramener.com/sanjay.yadav/pptgen
Author: Sanjay Yadav
Author-email: sanjay.yadav@gramener.com
License: Gramener
Keywords: powerpoint,ppt,pptx,office,open xml
Platform: UNKNOWN
Classifier: Development Status :: 3 - Alpha
Classifier: Environment :: Console
Classifier: Intended Audience :: Developers
Classifier: Operating System :: OS Independent
Classifier: Programming Language :: Python :: 2
Classifier: Programming Language :: Python :: 2.7
Classifier: Programming Language :: Python :: 3
Classifier: Programming Language :: Python :: 3.5
Classifier: Topic :: Office/Business :: Office Suites
Classifier: Topic :: Software Development :: Libraries
Requires-Dist: orderedattrdict (>=1.4.3)
Requires-Dist: pandas (>=0.19)
Requires-Dist: python-pptx (>=0.6.6)
Requires-Dist: pyyaml (>=3.10)
Requires-Dist: setuptools (>=16.0)
Requires-Dist: six
Requires-Dist: tornado (>=4.3)
